django_aai_eduhr/__init__.py
django_aai_eduhr/aai_attribute_map.py
django_aai_eduhr/apps.py
django_aai_eduhr/backends.py
django_aai_eduhr/signals.py
django_aai_eduhr/tests.py
django_aai_eduhr/urls.py
django_aai_eduhr/validators.py
django_aai_eduhr/management/__init__.py
django_aai_eduhr/management/commands/__init__.py
django_aai_eduhr/management/commands/aai_quickstart.py
django_aai_eduhr/migrations/__init__.py
django_aai_eduhr/models/__init__.py
django_aai_eduhr/models/enums/__init__.py
django_aai_eduhr/models/enums/org.py
django_aai_eduhr/models/enums/person.py
django_aai_eduhr/models/fields/__init__.py
django_aai_eduhr/models/fields/org.py
django_aai_eduhr/models/fields/person.py
django_aai_eduhr-1.0.0.dist-info/METADATA
django_aai_eduhr-1.0.0.dist-info/WHEEL
django_aai_eduhr-1.0.0.dist-info/top_level.txt
django_aai_eduhr-1.0.0.dist-info/RECORD
