Metadata-Version: 2.4
Name: django-aai-eduhr
Version: 1.0.0
Summary: A Django application for integrating with the AAI@EduHr Single Sign-On (SSO) Service.
Author-email: Dino Aljević <dino.aljevic@uniri.hr>
License-Expression: MIT
Project-URL: Homepage, https://github.com/fidit-rijeka/django-aai-eduhr
Project-URL: Issues, https://github.com/fidit-rijeka/django-aai-eduhr/issues
Classifier: Development Status :: 4 - Beta
Classifier: Environment :: Web Environment
Classifier: Framework :: Django
Classifier: Framework :: Django :: 4.2
Classifier: Framework :: Django :: 5.0
Classifier: Framework :: Django :: 5.1
Classifier: Intended Audience :: Developers
Classifier: Operating System :: OS Independent
Classifier: Programming Language :: Python
Classifier: Programming Language :: Python :: 3
Classifier: Topic :: Internet :: WWW/HTTP
Classifier: Topic :: Internet :: WWW/HTTP :: Dynamic Content
Requires-Python: >=3.8
Requires-Dist: django<5.0,>=4.2
Requires-Dist: djangosaml2<2.0.0,>=1.9.3
Requires-Dist: pysaml2<7.6.0,>=7.5.0
Requires-Dist: python-dateutil<2.10.0,>=2.9.0
